{
    "programmers": [{
        "name": "Bill Gates",
        "age": 43,
        "email": "bg@msn.com",
        "skill": {
            "C": 5,
            "C++": 6,
            "C#": 4,
            "JavaScript": 5,
            "Java": 7,
            "Python": 3,
            "Ruby": 2,
            "Perl": 4,
            "PHP": 5,
            "Objective-C": 6,
            "Scala": 4,
            "Swift": 3,
            "TypeScript": 3
        }
    }, {
        "name": "Sergey Brin",
        "age": 33,
        "email": "sb@gmail.com",
        "skill": {
            "JavaScript": 5,
            "Java": 7,
            "Python": 3,
            "Ruby": 2,
            "Perl": 4,
            "PHP": 5,
            "Scala": 4,
            "Swift": 3,
            "TypeScript": 3
        }
    }, {
        "name": "Larry Page",
        "age": 34,
        "email": "lp@gmail.com",
        "skill": {
            "C": 5,
            "C++": 6,
            "C#": 4,
            "Java": 7,
            "Python": 3,
            "Ruby": 2,
            "Perl": 4,
            "Objective-C": 6,
            "Scala": 4,
            "Swift": 3
        }
    }]
}